odoo/addons/invoice_inside_account_menu/README.rst
odoo/addons/invoice_inside_account_menu/__init__.py
odoo/addons/invoice_inside_account_menu/__manifest__.py
odoo/addons/invoice_inside_account_menu/static/description/icon.png
odoo/addons/invoice_inside_account_menu/views/invoicing_in_accouting.xml
odoo14_addon_invoice_inside_account_menu-14.0.1.0.1.dev1.dist-info/METADATA
odoo14_addon_invoice_inside_account_menu-14.0.1.0.1.dev1.dist-info/WHEEL
odoo14_addon_invoice_inside_account_menu-14.0.1.0.1.dev1.dist-info/top_level.txt
odoo14_addon_invoice_inside_account_menu-14.0.1.0.1.dev1.dist-info/RECORD
